getipping.py
getipping-0.0.1.dist-info/WHEEL
getipping-0.0.1.dist-info/METADATA
getipping-0.0.1.dist-info/RECORD
