Metadata-Version: 2.1
Name: getipping
Version: 0.0.1
Summary: Do you want to know the ip or ping? If yes, then write this country and find out the ip site: getip.ip ("site.site", port). If you want to see the ping enter this line: getip.ping ("site.site")
Author: TikOt Studio
Author-email: tikotstudio@yandex.ru
Requires-Python: >=3.7,<4.0
Classifier: Programming Language :: Python :: 3
Classifier: Programming Language :: Python :: 3.7
Classifier: Programming Language :: Python :: 3.8
Classifier: Programming Language :: Python :: 3.9
